<DOMSymbolItem xmlns:xsi="http://www.w3.org/2001/XMLSchema-instance" xmlns="http://ns.adobe.com/xfl/2008/" name="FlashAICB Assets_35/Layer 13/&amp;#060Group&amp;#062_1" itemID="5747c683-0000032e" lastModified="1464321667">
  <timeline>
    <DOMTimeline name="&amp;#060Group&amp;#062_1">
      <layers>
        <DOMLayer name="Layer 1" color="#4F80FF" current="true" isSelected="true">
          <frames>
            <DOMFrame index="0" keyMode="9728">
              <elements>
                <DOMGroup selected="true">
                  <members>
                    <DOMGroup selected="true">
                      <members>
                        <DOMShape selected="true" isDrawingObject="true">
                          <fills>
                            <FillStyle index="1">
                              <SolidColor color="#71181A"/>
                            </FillStyle>
                          </fills>
                          <edges>
                            <Edge fillStyle0="1" edges="!26 46[103 32 162 68!162 68[197 90 267 154!267 154[277 162 299 172!299 172[321 183 330 190!330 190[375 222 380 269!380 269[382 289 371 360!371 360[361 430 413 465!413 465[483 514 497 546!497 546[499 551 523 645!523 645[537 702 572 732
!572 732[665 811 778 721!778 721[794 709 779 694!779 694[764 679 748 692!748 692[637 781 588 685!588 685[574 658 556 593!556 593[539 529 528 509!528 509[518 488 501 477!501 477[478 465 462 453!462 453|437 442!437 442[401 378 427 317!427
 317[438 280 436 257!436 257[432 203 371 164!371 164[271 99 270 98!270 98[208 38 155 16!155 16[93 -9 15 6!15 6[-4 10 1 30!1 30[7 50 26 46"/>
                            <Edge cubics="!26 46(;145,24 188,91 267,154q26 46Q103 32q162 68Q197 90q267 154);"/>
                            <Edge cubics="!267 154(267,154;287,169 311,176 330,190q267 154Q277 162q299 172Q321 183q330 190)330,190;"/>
                            <Edge cubics="!330 190(330,190;398,239 381,295 371,360q330 190Q375 222q380 269Q382 289q371 360);"/>
                            <Edge cubics="!371 360(;353,483 459,456 497,546q371 360Q361 430q413 465Q483 514q497 546);"/>
                            <Edge cubics="!497 546(;524,612 513,682 572,732q497 546Q499 551q523 645Q537 702q572 732);"/>
                            <Edge cubics="!572 732(;640,790 713,773 778,721q572 732Q665 811q778 721);"/>
                            <Edge cubics="!778 721(;799,705 769,675 748,692q778 721Q794 709q779 694Q764 679q748 692);"/>
                            <Edge cubics="!748 692(;570,834 572,593 528,509q748 692Q637 781q588 685Q574 658q556 593Q539 529q528 509);"/>
                            <Edge cubics="!528 509(;511,475 494,477 462,453q528 509Q518 488q501 477Q478 465q462 453);"/>
                            <Edge cubics="!462 453(;454,449 446,445 437,442q462 453 437 442);"/>
                            <Edge cubics="!437 442(;413,399 410,357 427,317q437 442Q401 378q427 317);"/>
                            <Edge cubics="!427 317(;429,296 438,280 436,257q427 317Q438 280q436 257);"/>
                            <Edge cubics="!436 257(;429,167 325,151 270,98q436 257Q432 203q371 164Q271 99q270 98);"/>
                            <Edge cubics="!270 98(;194,24 125,-15 15,6q270 98Q208 38q155 16Q93 -9q15 6);"/>
                            <Edge cubics="!15 6(;-11,11 0,51 26,46q15 6Q-4 10q1 30Q7 50q26 46);"/>
                          </edges>
                        </DOMShape>
                      </members>
                    </DOMGroup>
                    <DOMGroup selected="true">
                      <members>
                        <DOMShape selected="true" isDrawingObject="true">
                          <fills>
                            <FillStyle index="1">
                              <SolidColor color="#71181A"/>
                            </FillStyle>
                          </fills>
                          <edges>
                            <Edge fillStyle0="1" edges="
!537 524[560 473 600 477!600 477|621 482!621 482[650 486 694 476!694 476[716 471 737 445!737 445[769 406 772 403!772 403[787 390 772 375!772 375[757 360 742 373!742 373[734 381 720 399!720 399[707 418 698 425!698 425[672 448 625 440!625
 440[600 435 589 433!589 433[569 431 552 440!552 440[522 456 497 513!497 513[489 532 509 537!509 537[530 543 537 524"/>
                            <Edge cubics="!537 524(;550,495 566,474 600,477q537 524Q560 473q600 477);"/>
                            <Edge cubics="!600 477(;607,478 614,481 621,482q600 477 621 482);"/>
                            <Edge cubics="!621 482(;643,485 672,481 694,476q621 482Q650 486q694 476);"/>
                            <Edge cubics="!694 476(;731,467 745,427 772,403q694 476Q716 471q737 445Q769 406q772 403);"/>
                            <Edge cubics="!772 403(;792,385 762,355 742,373q772 403Q787 390q772 375Q757 360q742 373);"/>
                            <Edge cubics="!742 373(;725,388 715,410 698,425q742 373Q734 381q720 399Q707 418q698 425);"/>
                            <Edge cubics="!698 425(;681,440 649,444 625,440q698 425Q672 448q625 440);"/>
                            <Edge cubics="!625 440(;598,436 579,426 552,440q625 440Q600 435q589 433Q569 431q552 440);"/>
                            <Edge cubics="!552 440(;523,455 509,485 497,513q552 440Q522 456q497 513);"/>
                            <Edge cubics="!497 513(;486,538 527,549 537,524q497 513Q489 532q509 537Q530 543q537 524);"/>
                          </edges>
                        </DOMShape>
                      </members>
                    </DOMGroup>
                    <DOMGroup selected="true">
                      <members>
                        <DOMShape selected="true" isDrawingObject="true">
                          <fills>
                            <FillStyle index="1">
                              <SolidColor color="#71181A"/>
                            </FillStyle>
                          </fills>
                          <edges>
                            <Edge fillStyle0="1" edges="
!451 481[403 505 404 561!404 561[405 593 409 661!409 661[402 706 336 762!336 762[269 818 261 856!261 856[257 876 277 882!277 882[297 887 301 867!301 867[305 851 330 828!330 828[359 804 368 794!368 794[420 744 439 704!439 704[446 688 445
 603!445 603[444 532 472 518!472 518[491 509 480 491!480 491[470 473 451 481"/>
                            <Edge cubics="!451 481(;372,520 419,595 409,661q451 481Q403 505q404 561Q405 593q409 661);"/>
                            <Edge cubics="!409 661(;395,748 278,777 261,856q409 661Q402 706q336 762Q269 818q261 856);"/>
                            <Edge cubics="!261 856(;255,883 295,894 301,867q261 856Q257 876q277 882Q297 887q301 867);"/>
                            <Edge cubics="!301 867(;307,840 350,813 368,794q301 867Q305 851q330 828Q359 804q368 794);"/>
                            <Edge cubics="!368 794(;395,768 423,738 439,704q368 794Q420 744q439 704);"/>
                            <Edge cubics="!439 704(;460,658 423,542 472,518q439 704Q446 688q445 603Q444 532q472 518);"/>
                            <Edge cubics="!472 518(;497,506 476,470 451,481q472 518Q491 509q480 491Q470 473q451 481);"/>
                          </edges>
                        </DOMShape>
                      </members>
                    </DOMGroup>
                  </members>
                </DOMGroup>
              </elements>
            </DOMFrame>
          </frames>
        </DOMLayer>
      </layers>
    </DOMTimeline>
  </timeline>
</DOMSymbolItem>