<DOMSymbolItem xmlns:xsi="http://www.w3.org/2001/XMLSchema-instance" xmlns="http://ns.adobe.com/xfl/2008/" name="FlashAICB Assets_34/Layer 13/&amp;#060Path&amp;#062_1" itemID="5747c654-00000324" lastModified="1464321620">
  <timeline>
    <DOMTimeline name="&amp;#060Path&amp;#062_1">
      <layers>
        <DOMLayer name="Layer 1" color="#4F80FF" current="true" isSelected="true">
          <frames>
            <DOMFrame index="0" keyMode="9728">
              <elements>
                <DOMShape selected="true" isDrawingObject="true">
                  <fills>
                    <FillStyle index="1">
                      <SolidColor color="#FFFFFF"/>
                    </FillStyle>
                  </fills>
                  <edges>
                    <Edge fillStyle0="1" edges="!386 1159[462 1125 594 972!594 972[721 824 755 739!755 739[781 673 804 575!804 575[829 463 842 407!842 407[874 273 876 210!876 210[880 99 824 34!824 34[799 7 775 2!775 2[735 -8 702 29!702 29[671 63 667 110!667 110[678 265 631 488!631
 488[611 580 567 653!567 653[519 733 447 778!447 778[409 802 337 830!337 830[243 868 108 930!108 930[67 950 48 964!48 964[17 987 6 1016!6 1016[-11 1060 18 1109!18 1109[42 1152 89 1184!89 1184[171 1240 247 1240!247 1240[291 1239 329 1218
!329 1218[369 1196 386 1159"/>
                    <Edge cubics="!386 1159(;491,1112 712,846 755,739q386 1159Q462 1125q594 972Q721 824q755 739);"/>
                    <Edge cubics="!755 739(;797,633 815,519 842,407q755 739Q781 673q804 575Q829 463q842 407);"/>
                    <Edge cubics="!842 407(842,407;872,281 909,132 824,34q842 407Q874 273q876 210Q880 99q824 34)824,34;"/>
                    <Edge cubics="!824 34(824,34;810,19 794,6 775,2q824 34Q799 7q775 2);"/>
                    <Edge cubics="!775 2(;719,-12 672,52 667,110q775 2Q735 -8q702 29Q671 63q667 110);"/>
                    <Edge cubics="!667 110(;675,227 655,373 631,488q667 110Q678 265q631 488);"/>
                    <Edge cubics="!631 488(;606,603 547,715 447,778q631 488Q611 580q567 653Q519 733q447 778);"/>
                    <Edge cubics="!447 778(;413,799 375,815 337,830q447 778Q409 802q337 830);"/>
                    <Edge cubics="!337 830(;260,861 184,895 108,930q337 830Q243 868q108 930);"/>
                    <Edge cubics="!108 930(;67,950 22,973 6,1016q108 930Q67 950q48 964Q17 987q6 1016);"/>
                    <Edge cubics="!6 1016(;-18,1079 34,1146 89,1184q6 1016Q-11 1060q18 1109Q42 1152q89 1184);"/>
                    <Edge cubics="!89 1184(;136,1216 190,1240 247,1240q89 1184Q171 1240q247 1240);"/>
                    <Edge cubics="!247 1240(;303,1239 362,1210 386,1159q247 1240Q291 1239q329 1218Q369 1196q386 1159);"/>
                  </edges>
                </DOMShape>
              </elements>
            </DOMFrame>
          </frames>
        </DOMLayer>
      </layers>
    </DOMTimeline>
  </timeline>
</DOMSymbolItem>